{
  "Terrain": [
    {
      "vert": [
        {
          "x": 0,
          "y": 375
        },
        {
          "x": 165,
          "y": 435
        },
        {
          "x": 285,
          "y": 375
        },
        {
          "x": 390,
          "y": 420
        },
        {
          "x": 435,
          "y": 465
        },
        {
          "x": 405,
          "y": 600
        },
        {
          "x": 510,
          "y": 675
        },
        {
          "x": 690,
          "y": 750
        },
        {
          "x": 780,
          "y": 615
        },
        {
          "x": 675,
          "y": 525
        },
        {
          "x": 705,
          "y": 345
        },
        {
          "x": 645,
          "y": 210
        },
        {
          "x": 570,
          "y": 255
        },
        {
          "x": 420,
          "y": 270
        },
        {
          "x": 330,
          "y": 330
        },
        {
          "x": 210,
          "y": 315
        },
        {
          "x": 120,
          "y": 375
        }
      ],
      "sides": [
        {
          "p1": {
            "x": 0,
            "y": 375
          },
          "p2": {
            "x": 165,
            "y": 435
          },
          "slope": 0.36363636363636365
        },
        {
          "p1": {
            "x": 165,
            "y": 435
          },
          "p2": {
            "x": 285,
            "y": 375
          },
          "slope": -0.5
        },
        {
          "p1": {
            "x": 285,
            "y": 375
          },
          "p2": {
            "x": 390,
            "y": 420
          },
          "slope": 0.42857142857142855
        },
        {
          "p1": {
            "x": 390,
            "y": 420
          },
          "p2": {
            "x": 435,
            "y": 465
          },
          "slope": 1
        },
        {
          "p1": {
            "x": 435,
            "y": 465
          },
          "p2": {
            "x": 405,
            "y": 600
          },
          "slope": -4.5
        },
        {
          "p1": {
            "x": 405,
            "y": 600
          },
          "p2": {
            "x": 510,
            "y": 675
          },
          "slope": 0.7142857142857143
        },
        {
          "p1": {
            "x": 510,
            "y": 675
          },
          "p2": {
            "x": 690,
            "y": 750
          },
          "slope": 0.4166666666666667
        },
        {
          "p1": {
            "x": 690,
            "y": 750
          },
          "p2": {
            "x": 780,
            "y": 615
          },
          "slope": -1.5
        },
        {
          "p1": {
            "x": 780,
            "y": 615
          },
          "p2": {
            "x": 675,
            "y": 525
          },
          "slope": 0.8571428571428571
        },
        {
          "p1": {
            "x": 675,
            "y": 525
          },
          "p2": {
            "x": 705,
            "y": 345
          },
          "slope": -6
        },
        {
          "p1": {
            "x": 705,
            "y": 345
          },
          "p2": {
            "x": 645,
            "y": 210
          },
          "slope": 2.25
        },
        {
          "p1": {
            "x": 645,
            "y": 210
          },
          "p2": {
            "x": 570,
            "y": 255
          },
          "slope": -0.6
        },
        {
          "p1": {
            "x": 570,
            "y": 255
          },
          "p2": {
            "x": 420,
            "y": 270
          },
          "slope": -0.1
        },
        {
          "p1": {
            "x": 420,
            "y": 270
          },
          "p2": {
            "x": 330,
            "y": 330
          },
          "slope": -0.6666666666666666
        },
        {
          "p1": {
            "x": 330,
            "y": 330
          },
          "p2": {
            "x": 210,
            "y": 315
          },
          "slope": 0.125
        },
        {
          "p1": {
            "x": 210,
            "y": 315
          },
          "p2": {
            "x": 120,
            "y": 375
          },
          "slope": -0.6666666666666666
        },
        {
          "p1": {
            "x": 120,
            "y": 375
          },
          "p2": {
            "x": 0,
            "y": 375
          },
          "slope": 0
        }
      ],
      "vel": {
        "isPInst": true,
        "x": 0,
        "y": 0,
        "z": 0
      },
      "pos": {
        "x": 431.47058823529414,
        "y": 431.47058823529414
      },
      "max": 435.1503140843987
    },
    {
      "vert": [
        {
          "x": 30,
          "y": 495
        },
        {
          "x": 105,
          "y": 510
        },
        {
          "x": 195,
          "y": 495
        },
        {
          "x": 285,
          "y": 480
        },
        {
          "x": 345,
          "y": 525
        },
        {
          "x": 330,
          "y": 600
        },
        {
          "x": 345,
          "y": 660
        },
        {
          "x": 405,
          "y": 720
        },
        {
          "x": 525,
          "y": 765
        },
        {
          "x": 615,
          "y": 810
        },
        {
          "x": 645,
          "y": 795
        },
        {
          "x": 705,
          "y": 825
        },
        {
          "x": 15,
          "y": 825
        },
        {
          "x": 15,
          "y": 510
        }
      ],
      "sides": [
        {
          "p1": {
            "x": 30,
            "y": 495
          },
          "p2": {
            "x": 105,
            "y": 510
          },
          "slope": 0.2
        },
        {
          "p1": {
            "x": 105,
            "y": 510
          },
          "p2": {
            "x": 195,
            "y": 495
          },
          "slope": -0.16666666666666666
        },
        {
          "p1": {
            "x": 195,
            "y": 495
          },
          "p2": {
            "x": 285,
            "y": 480
          },
          "slope": -0.16666666666666666
        },
        {
          "p1": {
            "x": 285,
            "y": 480
          },
          "p2": {
            "x": 345,
            "y": 525
          },
          "slope": 0.75
        },
        {
          "p1": {
            "x": 345,
            "y": 525
          },
          "p2": {
            "x": 330,
            "y": 600
          },
          "slope": -5
        },
        {
          "p1": {
            "x": 330,
            "y": 600
          },
          "p2": {
            "x": 345,
            "y": 660
          },
          "slope": 4
        },
        {
          "p1": {
            "x": 345,
            "y": 660
          },
          "p2": {
            "x": 405,
            "y": 720
          },
          "slope": 1
        },
        {
          "p1": {
            "x": 405,
            "y": 720
          },
          "p2": {
            "x": 525,
            "y": 765
          },
          "slope": 0.375
        },
        {
          "p1": {
            "x": 525,
            "y": 765
          },
          "p2": {
            "x": 615,
            "y": 810
          },
          "slope": 0.5
        },
        {
          "p1": {
            "x": 615,
            "y": 810
          },
          "p2": {
            "x": 645,
            "y": 795
          },
          "slope": -0.5
        },
        {
          "p1": {
            "x": 645,
            "y": 795
          },
          "p2": {
            "x": 705,
            "y": 825
          },
          "slope": 0.5
        },
        {
          "p1": {
            "x": 705,
            "y": 825
          },
          "p2": {
            "x": 15,
            "y": 825
          },
          "slope": 0
        },
        {
          "p1": {
            "x": 15,
            "y": 825
          },
          "p2": {
            "x": 15,
            "y": 510
          },
          "slope": null
        },
        {
          "p1": {
            "x": 15,
            "y": 510
          },
          "p2": {
            "x": 30,
            "y": 495
          },
          "slope": -1
        }
      ],
      "vel": {
        "isPInst": true,
        "x": 0,
        "y": 0,
        "z": 0
      },
      "pos": {
        "x": 325.7142857142857,
        "y": 643.9285714285714
      },
      "max": 420.2909888471587
    },
    {
      "vert": [
        {
          "x": 825,
          "y": 705
        },
        {
          "x": 765,
          "y": 705
        },
        {
          "x": 750,
          "y": 765
        },
        {
          "x": 720,
          "y": 780
        },
        {
          "x": 735,
          "y": 825
        },
        {
          "x": 795,
          "y": 825
        },
        {
          "x": 825,
          "y": 780
        }
      ],
      "sides": [
        {
          "p1": {
            "x": 825,
            "y": 705
          },
          "p2": {
            "x": 765,
            "y": 705
          },
          "slope": 0
        },
        {
          "p1": {
            "x": 765,
            "y": 705
          },
          "p2": {
            "x": 750,
            "y": 765
          },
          "slope": -4
        },
        {
          "p1": {
            "x": 750,
            "y": 765
          },
          "p2": {
            "x": 720,
            "y": 780
          },
          "slope": -0.5
        },
        {
          "p1": {
            "x": 720,
            "y": 780
          },
          "p2": {
            "x": 735,
            "y": 825
          },
          "slope": 3
        },
        {
          "p1": {
            "x": 735,
            "y": 825
          },
          "p2": {
            "x": 795,
            "y": 825
          },
          "slope": 0
        },
        {
          "p1": {
            "x": 795,
            "y": 825
          },
          "p2": {
            "x": 825,
            "y": 780
          },
          "slope": -1.5
        },
        {
          "p1": {
            "x": 825,
            "y": 780
          },
          "p2": {
            "x": 825,
            "y": 705
          },
          "slope": null
        }
      ],
      "vel": {
        "isPInst": true,
        "x": 0,
        "y": 0,
        "z": 0
      },
      "pos": {
        "x": 773.5714285714286,
        "y": 769.2857142857143
      },
      "max": 82.3258830527081
    },
    {
      "vert": [
        {
          "x": 795,
          "y": 660
        },
        {
          "x": 765,
          "y": 675
        },
        {
          "x": 810,
          "y": 675
        }
      ],
      "sides": [
        {
          "p1": {
            "x": 795,
            "y": 660
          },
          "p2": {
            "x": 765,
            "y": 675
          },
          "slope": -0.5
        },
        {
          "p1": {
            "x": 765,
            "y": 675
          },
          "p2": {
            "x": 810,
            "y": 675
          },
          "slope": 0
        },
        {
          "p1": {
            "x": 810,
            "y": 675
          },
          "p2": {
            "x": 795,
            "y": 660
          },
          "slope": 1
        }
      ],
      "vel": {
        "isPInst": true,
        "x": 0,
        "y": 0,
        "z": 0
      },
      "pos": {
        "x": 790,
        "y": 670
      },
      "max": 25.495097567963924
    },
    {
      "vert": [
        {
          "x": 705,
          "y": 510
        },
        {
          "x": 750,
          "y": 330
        },
        {
          "x": 795,
          "y": 360
        },
        {
          "x": 795,
          "y": 570
        }
      ],
      "sides": [
        {
          "p1": {
            "x": 705,
            "y": 510
          },
          "p2": {
            "x": 750,
            "y": 330
          },
          "slope": -4
        },
        {
          "p1": {
            "x": 750,
            "y": 330
          },
          "p2": {
            "x": 795,
            "y": 360
          },
          "slope": 0.6666666666666666
        },
        {
          "p1": {
            "x": 795,
            "y": 360
          },
          "p2": {
            "x": 795,
            "y": 570
          },
          "slope": null
        },
        {
          "p1": {
            "x": 795,
            "y": 570
          },
          "p2": {
            "x": 705,
            "y": 510
          },
          "slope": 0.6666666666666666
        }
      ],
      "vel": {
        "isPInst": true,
        "x": 0,
        "y": 0,
        "z": 0
      },
      "pos": {
        "x": 761.25,
        "y": 442.5
      },
      "max": 131.8912904630173
    },
    {
      "vert": [
        {
          "x": 690,
          "y": 180
        },
        {
          "x": 765,
          "y": 300
        },
        {
          "x": 765,
          "y": 135
        },
        {
          "x": 360,
          "y": 105
        },
        {
          "x": 255,
          "y": 165
        }
      ],
      "sides": [
        {
          "p1": {
            "x": 690,
            "y": 180
          },
          "p2": {
            "x": 765,
            "y": 300
          },
          "slope": 1.6
        },
        {
          "p1": {
            "x": 765,
            "y": 300
          },
          "p2": {
            "x": 765,
            "y": 135
          },
          "slope": null
        },
        {
          "p1": {
            "x": 765,
            "y": 135
          },
          "p2": {
            "x": 360,
            "y": 105
          },
          "slope": 0.07407407407407407
        },
        {
          "p1": {
            "x": 360,
            "y": 105
          },
          "p2": {
            "x": 255,
            "y": 165
          },
          "slope": -0.5714285714285714
        },
        {
          "p1": {
            "x": 255,
            "y": 165
          },
          "p2": {
            "x": 690,
            "y": 180
          },
          "slope": 0.034482758620689655
        }
      ],
      "vel": {
        "isPInst": true,
        "x": 0,
        "y": 0,
        "z": 0
      },
      "pos": {
        "x": 567,
        "y": 177
      },
      "max": 312.23068395018447
    },
    {
      "vert": [
        {
          "x": 675,
          "y": 15
        },
        {
          "x": 735,
          "y": 75
        },
        {
          "x": 840,
          "y": 90
        }
      ],
      "sides": [
        {
          "p1": {
            "x": 675,
            "y": 15
          },
          "p2": {
            "x": 735,
            "y": 75
          },
          "slope": 1
        },
        {
          "p1": {
            "x": 735,
            "y": 75
          },
          "p2": {
            "x": 840,
            "y": 90
          },
          "slope": 0.14285714285714285
        },
        {
          "p1": {
            "x": 840,
            "y": 90
          },
          "p2": {
            "x": 675,
            "y": 15
          },
          "slope": 0.45454545454545453
        }
      ],
      "vel": {
        "isPInst": true,
        "x": 0,
        "y": 0,
        "z": 0
      },
      "pos": {
        "x": 750,
        "y": 60
      },
      "max": 94.86832980505139
    },
    {
      "vert": [
        {
          "x": 210,
          "y": 75
        },
        {
          "x": 210,
          "y": 120
        },
        {
          "x": 180,
          "y": 105
        }
      ],
      "sides": [
        {
          "p1": {
            "x": 210,
            "y": 75
          },
          "p2": {
            "x": 210,
            "y": 120
          },
          "slope": null
        },
        {
          "p1": {
            "x": 210,
            "y": 120
          },
          "p2": {
            "x": 180,
            "y": 105
          },
          "slope": 0.5
        },
        {
          "p1": {
            "x": 180,
            "y": 105
          },
          "p2": {
            "x": 210,
            "y": 75
          },
          "slope": -1
        }
      ],
      "vel": {
        "isPInst": true,
        "x": 0,
        "y": 0,
        "z": 0
      },
      "pos": {
        "x": 200,
        "y": 100
      },
      "max": 26.925824035672523
    },
    {
      "vert": [
        {
          "x": 195,
          "y": 150
        },
        {
          "x": 195,
          "y": 195
        },
        {
          "x": 165,
          "y": 180
        }
      ],
      "sides": [
        {
          "p1": {
            "x": 195,
            "y": 150
          },
          "p2": {
            "x": 195,
            "y": 195
          },
          "slope": null
        },
        {
          "p1": {
            "x": 195,
            "y": 195
          },
          "p2": {
            "x": 165,
            "y": 180
          },
          "slope": 0.5
        },
        {
          "p1": {
            "x": 165,
            "y": 180
          },
          "p2": {
            "x": 195,
            "y": 150
          },
          "slope": -1
        }
      ],
      "vel": {
        "isPInst": true,
        "x": 0,
        "y": 0,
        "z": 0
      },
      "pos": {
        "x": 185,
        "y": 175
      },
      "max": 26.925824035672523
    },
    {
      "vert": [
        {
          "x": 195,
          "y": 225
        },
        {
          "x": 195,
          "y": 255
        }
      ],
      "sides": [
        {
          "p1": {
            "x": 195,
            "y": 225
          },
          "p2": {
            "x": 195,
            "y": 255
          },
          "slope": null
        },
        {
          "p1": {
            "x": 195,
            "y": 255
          },
          "p2": {
            "x": 195,
            "y": 225
          },
          "slope": null
        }
      ],
      "vel": {
        "isPInst": true,
        "x": 0,
        "y": 0,
        "z": 0
      },
      "pos": {
        "x": 195,
        "y": 240
      },
      "max": 15
    },
    {
      "vert": [
        {
          "x": 195,
          "y": 225
        },
        {
          "x": 195,
          "y": 255
        },
        {
          "x": 165,
          "y": 240
        }
      ],
      "sides": [
        {
          "p1": {
            "x": 195,
            "y": 225
          },
          "p2": {
            "x": 195,
            "y": 255
          },
          "slope": null
        },
        {
          "p1": {
            "x": 195,
            "y": 255
          },
          "p2": {
            "x": 165,
            "y": 240
          },
          "slope": 0.5
        },
        {
          "p1": {
            "x": 165,
            "y": 240
          },
          "p2": {
            "x": 195,
            "y": 225
          },
          "slope": -0.5
        }
      ],
      "vel": {
        "isPInst": true,
        "x": 0,
        "y": 0,
        "z": 0
      },
      "pos": {
        "x": 185,
        "y": 240
      },
      "max": 20
    },
    {
      "vert": [
        {
          "x": 375,
          "y": 195
        },
        {
          "x": 390,
          "y": 255
        },
        {
          "x": 255,
          "y": 300
        },
        {
          "x": 255,
          "y": 195
        }
      ],
      "sides": [
        {
          "p1": {
            "x": 375,
            "y": 195
          },
          "p2": {
            "x": 390,
            "y": 255
          },
          "slope": 4
        },
        {
          "p1": {
            "x": 390,
            "y": 255
          },
          "p2": {
            "x": 255,
            "y": 300
          },
          "slope": -0.3333333333333333
        },
        {
          "p1": {
            "x": 255,
            "y": 300
          },
          "p2": {
            "x": 255,
            "y": 195
          },
          "slope": null
        },
        {
          "p1": {
            "x": 255,
            "y": 195
          },
          "p2": {
            "x": 375,
            "y": 195
          },
          "slope": 0
        }
      ],
      "vel": {
        "isPInst": true,
        "x": 0,
        "y": 0,
        "z": 0
      },
      "pos": {
        "x": 318.75,
        "y": 236.25
      },
      "max": 90.15611460128481
    },
    {
      "vert": [
        {
          "x": 420,
          "y": 15
        },
        {
          "x": 405,
          "y": 75
        },
        {
          "x": 450,
          "y": 75
        },
        {
          "x": 465,
          "y": 15
        }
      ],
      "sides": [
        {
          "p1": {
            "x": 420,
            "y": 15
          },
          "p2": {
            "x": 405,
            "y": 75
          },
          "slope": -4
        },
        {
          "p1": {
            "x": 405,
            "y": 75
          },
          "p2": {
            "x": 450,
            "y": 75
          },
          "slope": 0
        },
        {
          "p1": {
            "x": 450,
            "y": 75
          },
          "p2": {
            "x": 465,
            "y": 15
          },
          "slope": -4
        },
        {
          "p1": {
            "x": 465,
            "y": 15
          },
          "p2": {
            "x": 420,
            "y": 15
          },
          "slope": 0
        }
      ],
      "vel": {
        "isPInst": true,
        "x": 0,
        "y": 0,
        "z": 0
      },
      "pos": {
        "x": 435,
        "y": 45
      },
      "max": 42.42640687119285
    },
    {
      "vert": [
        {
          "x": 465,
          "y": 120
        },
        {
          "x": 480,
          "y": 75
        },
        {
          "x": 510,
          "y": 75
        },
        {
          "x": 510,
          "y": 135
        }
      ],
      "sides": [
        {
          "p1": {
            "x": 465,
            "y": 120
          },
          "p2": {
            "x": 480,
            "y": 75
          },
          "slope": -3
        },
        {
          "p1": {
            "x": 480,
            "y": 75
          },
          "p2": {
            "x": 510,
            "y": 75
          },
          "slope": 0
        },
        {
          "p1": {
            "x": 510,
            "y": 75
          },
          "p2": {
            "x": 510,
            "y": 135
          },
          "slope": null
        },
        {
          "p1": {
            "x": 510,
            "y": 135
          },
          "p2": {
            "x": 465,
            "y": 120
          },
          "slope": 0.3333333333333333
        }
      ],
      "vel": {
        "isPInst": true,
        "x": 0,
        "y": 0,
        "z": 0
      },
      "pos": {
        "x": 491.25,
        "y": 101.25
      },
      "max": 38.60861302870126
    },
    {
      "vert": [
        {
          "x": 615,
          "y": 240
        },
        {
          "x": 525,
          "y": 195
        },
        {
          "x": 465,
          "y": 285
        }
      ],
      "sides": [
        {
          "p1": {
            "x": 615,
            "y": 240
          },
          "p2": {
            "x": 525,
            "y": 195
          },
          "slope": 0.5
        },
        {
          "p1": {
            "x": 525,
            "y": 195
          },
          "p2": {
            "x": 465,
            "y": 285
          },
          "slope": -1.5
        },
        {
          "p1": {
            "x": 465,
            "y": 285
          },
          "p2": {
            "x": 615,
            "y": 240
          },
          "slope": -0.3
        }
      ],
      "vel": {
        "isPInst": true,
        "x": 0,
        "y": 0,
        "z": 0
      },
      "pos": {
        "x": 535,
        "y": 240
      },
      "max": 83.2165848854662
    }
  ],
  "WinZones": [
    {
      "vert": [
        {
          "x": 900,
          "y": 210
        },
        {
          "x": 120,
          "y": 390
        },
        {
          "x": 120,
          "y": 15
        },
        {
          "x": 15,
          "y": 15
        },
        {
          "x": 15,
          "y": 360
        }
      ],
      "sides": [
        {
          "p1": {
            "x": 900,
            "y": 210
          },
          "p2": {
            "x": 120,
            "y": 390
          },
          "slope": -0.23076923076923078
        },
        {
          "p1": {
            "x": 120,
            "y": 390
          },
          "p2": {
            "x": 120,
            "y": 15
          },
          "slope": null
        },
        {
          "p1": {
            "x": 120,
            "y": 15
          },
          "p2": {
            "x": 15,
            "y": 15
          },
          "slope": 0
        },
        {
          "p1": {
            "x": 15,
            "y": 15
          },
          "p2": {
            "x": 15,
            "y": 360
          },
          "slope": null
        },
        {
          "p1": {
            "x": 15,
            "y": 360
          },
          "p2": {
            "x": 900,
            "y": 210
          },
          "slope": -0.1694915254237288
        }
      ],
      "vel": {
        "isPInst": true,
        "x": 0,
        "y": 0,
        "z": 0
      },
      "pos": {
        "x": 234,
        "y": 198
      },
      "max": 666.1080993352355
    }
  ],
  "PlayerSpawns": [
    {
      "x": 75,
      "y": 465
    }
  ]
}
